<?xml version="1.0" encoding="UTF-8"?>
<media>
    <film>
        <titolo></titolo>
        <anno></anno>
        <genere></genere>
        <dataCreazione></dataCreazione>
        <ultimaModifica></ultimaModifica>
        <trama></trama>
        <distribuzione></distribuzione>
        <durata></durata>    
    </film>
    <serieTV>
        <titolo></titolo>
        <anno></anno>
        <genere></genere>
        <dataCreazione></dataCreazione>
        <ultimaModifica></ultimaModifica>
        <descrizione></descrizione>
        <stagione></stagione>
        <episodio></episodio>
        <lunghezza></lunghezza>    
    </serieTV>
</media>